scmver/__init__.py
scmver/__main__.py
scmver/__version__.py
scmver/_typing.py
scmver/bazaar.py
scmver/cli.py
scmver/core.py
scmver/darcs.py
scmver/fossil.py
scmver/git.py
scmver/mercurial.py
scmver/py.typed
scmver/setuptools.py
scmver/subversion.py
scmver/util.py
scmver-1.8.dist-info/LICENSE.txt
scmver-1.8.dist-info/METADATA
scmver-1.8.dist-info/WHEEL
scmver-1.8.dist-info/entry_points.txt
scmver-1.8.dist-info/top_level.txt
scmver-1.8.dist-info/RECORD
