Metadata-Version: 2.1
Name: scmver
Version: 1.8
Summary: A package version manager based on SCM tags
Author-email: Akinori Hattori <hattya@gmail.com>
License: MIT
Project-URL: Homepage, https://github.com/hattya/scmver
Classifier: Development Status :: 5 - Production/Stable
Classifier: Intended Audience :: Developers
Classifier: License :: OSI Approved :: MIT License
Classifier: Operating System :: OS Independent
Classifier: Programming Language :: Python :: 3
Classifier: Programming Language :: Python :: 3.9
Classifier: Programming Language :: Python :: 3.10
Classifier: Programming Language :: Python :: 3.11
Classifier: Programming Language :: Python :: 3.12
Classifier: Programming Language :: Python :: 3.13
Classifier: Topic :: Software Development :: Libraries :: Python Modules
Classifier: Topic :: Software Development :: Version Control
Classifier: Topic :: System :: Software Distribution
Classifier: Topic :: Utilities
Requires-Python: >=3.9
License-File: LICENSE.txt
Provides-Extra: cli
Requires-Dist: click ; extra == 'cli'
Provides-Extra: toml
Requires-Dist: tomli ; (python_version < "3.11") and extra == 'toml'
